tim.py
tim-0.5.dist-info/METADATA
tim-0.5.dist-info/top_level.txt
tim-0.5.dist-info/RECORD
tim-0.5.dist-info/DESCRIPTION.rst
tim-0.5.dist-info/WHEEL
tim-0.5.dist-info/metadata.json
