Metadata-Version: 1.0
Name: tim
Version: 0.5
Summary: TIM: Timed Iteration Monitor
Home-page: https://github.com/olethanh/tim
Author: Olivier Le Thanh Duong
Author-email: olivier@lethanh.be
License: WTFPL
Platform: UNKNOWN
